web3db/__init__.py
web3db/base.py
web3db/core.py
web3db/models/__init__.py
web3db/models/base.py
web3db/models/bybit.py
web3db/models/discord.py
web3db/models/email.py
web3db/models/github.py
web3db/models/mexc.py
web3db/models/mixins.py
web3db/models/profile.py
web3db/models/proxy.py
web3db/models/twitter.py
web3db/utils/__init__.py
web3db/utils/encrypt_private.py
web3db/utils/env.py
web3db/utils/logger.py
web3db-1.0.6.dist-info/METADATA
web3db-1.0.6.dist-info/WHEEL
web3db-1.0.6.dist-info/RECORD
