Metadata-Version: 2.1
Name: web3db
Version: 1.0.6
Summary: Database for web3
Home-page: https://github.com/timertimertimer/web3db
Author: timertimertimer
Author-email: timerkhan2002@gmail.com
Requires-Python: >=3.10,<4.0
Classifier: Programming Language :: Python :: 3
Classifier: Programming Language :: Python :: 3.10
Classifier: Programming Language :: Python :: 3.11
Requires-Dist: SQLAlchemy (>=2.0.29,<3.0.0)
Requires-Dist: aiosqlite (>=0.20.0,<0.21.0)
Requires-Dist: aptos-sdk (>=0.8.6,<0.9.0)
Requires-Dist: asyncpg (>=0.29.0,<0.30.0)
Requires-Dist: base58 (>=2.1.1,<3.0.0)
Requires-Dist: bitcoin-utils (>=0.6.6,<0.7.0)
Requires-Dist: eth-account (>=0.13.0,<0.14.0)
Requires-Dist: loguru (>=0.7.2,<0.8.0)
Requires-Dist: python-dotenv (>=1.0.1,<2.0.0)
Requires-Dist: python-gnupg (>=0.5.2,<0.6.0)
Requires-Dist: solana (>=0.33.0,<0.34.0)
Project-URL: Repository, https://github.com/timertimertimer/web3db
